{
  "annualChildren" : [ {
    "children" : [ {
      "id" : 1,
      "lastName" : "Mihalache",
      "firstName" : "Tudor",
      "city" : null,
      "age" : 17,
      "giftsPreferences" : [ "Books", "Board Games" ],
      "averageScore" : 4.0,
      "niceScoreHistory" : [ 4.0 ],
      "assignedBudget" : 1293.0,
      "receivedGifts" : [ {
        "productName" : "Diary of a Wimpy Kid",
        "price" : 25.0,
        "category" : "Books"
      }, {
        "productName" : "Monopoly",
        "price" : 30.0,
        "category" : "Board Games"
      } ]
    }, {
      "id" : 2,
      "lastName" : "Stoica",
      "firstName" : "Tudor",
      "city" : null,
      "age" : 3,
      "giftsPreferences" : [ "Books", "Clothes" ],
      "averageScore" : 10.0,
      "niceScoreHistory" : [ 9.0 ],
      "assignedBudget" : 3232.5,
      "receivedGifts" : [ {
        "productName" : "Diary of a Wimpy Kid",
        "price" : 25.0,
        "category" : "Books"
      }, {
        "productName" : "Shoes",
        "price" : 70.0,
        "category" : "Clothes"
      } ]
    }, {
      "id" : 3,
      "lastName" : "Pop",
      "firstName" : "Matei",
      "city" : null,
      "age" : 10,
      "giftsPreferences" : [ "Books", "Board Games" ],
      "averageScore" : 3.0,
      "niceScoreHistory" : [ 3.0 ],
      "assignedBudget" : 969.75,
      "receivedGifts" : [ {
        "productName" : "Diary of a Wimpy Kid",
        "price" : 25.0,
        "category" : "Books"
      }, {
        "productName" : "Monopoly",
        "price" : 30.0,
        "category" : "Board Games"
      } ]
    } ]
  }, {
    "children" : [ {
      "id" : 2,
      "lastName" : "Stoica",
      "firstName" : "Tudor",
      "city" : null,
      "age" : 4,
      "giftsPreferences" : [ "Books", "Clothes" ],
      "averageScore" : 10.0,
      "niceScoreHistory" : [ 9.0 ],
      "assignedBudget" : 2256.9230769230767,
      "receivedGifts" : [ {
        "productName" : "Diary of a Wimpy Kid",
        "price" : 25.0,
        "category" : "Books"
      }, {
        "productName" : "Shoes",
        "price" : 70.0,
        "category" : "Clothes"
      } ]
    }, {
      "id" : 3,
      "lastName" : "Pop",
      "firstName" : "Matei",
      "city" : null,
      "age" : 11,
      "giftsPreferences" : [ "Books", "Board Games" ],
      "averageScore" : 3.0,
      "niceScoreHistory" : [ 3.0 ],
      "assignedBudget" : 677.0769230769231,
      "receivedGifts" : [ {
        "productName" : "Diary of a Wimpy Kid",
        "price" : 25.0,
        "category" : "Books"
      }, {
        "productName" : "Monopoly",
        "price" : 30.0,
        "category" : "Board Games"
      } ]
    } ]
  }, {
    "children" : [ {
      "id" : 2,
      "lastName" : "Stoica",
      "firstName" : "Tudor",
      "city" : null,
      "age" : 5,
      "giftsPreferences" : [ "Books", "Clothes" ],
      "averageScore" : 9.0,
      "niceScoreHistory" : [ 9.0 ],
      "assignedBudget" : 2697.0,
      "receivedGifts" : [ {
        "productName" : "Diary of a Wimpy Kid",
        "price" : 25.0,
        "category" : "Books"
      }, {
        "productName" : "Shoes",
        "price" : 70.0,
        "category" : "Clothes"
      } ]
    }, {
      "id" : 3,
      "lastName" : "Pop",
      "firstName" : "Matei",
      "city" : null,
      "age" : 12,
      "giftsPreferences" : [ "Books", "Board Games" ],
      "averageScore" : 3.0,
      "niceScoreHistory" : [ 3.0 ],
      "assignedBudget" : 899.0,
      "receivedGifts" : [ {
        "productName" : "Diary of a Wimpy Kid",
        "price" : 25.0,
        "category" : "Books"
      }, {
        "productName" : "Monopoly",
        "price" : 30.0,
        "category" : "Board Games"
      } ]
    } ]
  }, {
    "children" : [ {
      "id" : 2,
      "lastName" : "Stoica",
      "firstName" : "Tudor",
      "city" : null,
      "age" : 6,
      "giftsPreferences" : [ "Books", "Clothes" ],
      "averageScore" : 9.0,
      "niceScoreHistory" : [ 9.0 ],
      "assignedBudget" : 1939.5,
      "receivedGifts" : [ {
        "productName" : "Diary of a Wimpy Kid",
        "price" : 25.0,
        "category" : "Books"
      }, {
        "productName" : "Shoes",
        "price" : 70.0,
        "category" : "Clothes"
      } ]
    }, {
      "id" : 3,
      "lastName" : "Pop",
      "firstName" : "Matei",
      "city" : null,
      "age" : 13,
      "giftsPreferences" : [ "Books", "Board Games" ],
      "averageScore" : 3.0,
      "niceScoreHistory" : [ 3.0 ],
      "assignedBudget" : 646.5,
      "receivedGifts" : [ {
        "productName" : "Diary of a Wimpy Kid",
        "price" : 25.0,
        "category" : "Books"
      }, {
        "productName" : "Monopoly",
        "price" : 30.0,
        "category" : "Board Games"
      } ]
    } ]
  } ]
}